README.rst
setup.cfg
setup.py
splunkapi3/__init__.py
splunkapi3/access_control.py
splunkapi3/client.py
splunkapi3/connection.py
splunkapi3/data.py
splunkapi3/rest.py
splunkapi3/status_codes.py
splunkapi3.egg-info/PKG-INFO
splunkapi3.egg-info/SOURCES.txt
splunkapi3.egg-info/dependency_links.txt
splunkapi3.egg-info/requires.txt
splunkapi3.egg-info/top_level.txt
splunkapi3/model/__init__.py
splunkapi3/model/control_action.py
splunkapi3/model/model.py
splunkapi3/model/options.py
splunkapi3/model/output_mode.py
splunkapi3/model/search_create.py
splunkapi3/model/search_result_options.py
splunkapi3/model/view_edit.py
splunkapi3/search/__init__.py
splunkapi3/search/alert.py
splunkapi3/search/command.py
splunkapi3/search/job.py
splunkapi3/search/saved.py
splunkapi3/search/search.py
splunkapi3/search/util.py
splunkapi3/search/view.py