Metadata-Version: 1.1
Name: splunkapi3
Version: 0.1.1
Summary: Splunk API for python 3.5
Home-page: https://github.com/swimlane/splunkapi3
Author: Dmitriy Krasnikov
Author-email: dmitriy.krasnikov@swimlane.com
License: MIT
Platform: UNKNOWN
Classifier: Development Status :: 3 - Alpha
Classifier: Intended Audience :: Developers
Classifier: License :: OSI Approved :: MIT License
Classifier: Operating System :: OS Independent
Classifier: Programming Language :: Python
Classifier: Programming Language :: Python :: 3.5
Classifier: Programming Language :: Python :: Implementation :: PyPy
